README.md
setup.py
cmdtime/__init__.py
cmdtime/__main__.py
cmdtime/cmdtime.py
cmdtime.egg-info/PKG-INFO
cmdtime.egg-info/SOURCES.txt
cmdtime.egg-info/dependency_links.txt
cmdtime.egg-info/entry_points.txt
cmdtime.egg-info/top_level.txt