Metadata-Version: 2.1
Name: cmdtime
Version: 0.0.3
Summary: Similar to Linux `time` utility useful for Windows Command Prompt using pure Python
Home-page: https://github.com/ravi-chandran/cmdtime
Author: Ravi Chandran
License: UNKNOWN
Platform: UNKNOWN
Classifier: Programming Language :: Python :: 3
Classifier: License :: OSI Approved :: MIT License
Classifier: Operating System :: OS Independent
Requires-Python: >=3.5
